process/__init__.py
process/admin.py
process/apps.py
process/conf.py
process/env.py
process/exceptions.py
process/forms.py
process/models.py
process/urls.py
process/management/__init__.py
process/management/commands/__init__.py
process/management/commands/_actions.py
process/management/commands/_task.py
process/management/commands/run_jobs.py
process/migrations/__init__.py
process/static/process/css/pr_highcharts.css
process/static/process/css/pr_organization.css
process/static/process/images/bash.png
process/static/process/images/cancel.png
process/static/process/images/delete.png
process/static/process/images/flow-chart.png
process/static/process/images/history.png
process/static/process/images/list-icon.png
process/static/process/images/perl.png
process/static/process/images/python.png
process/static/process/images/run.png
process/static/process/js/pr_exporting.js
process/static/process/js/pr_highcharts.js
process/static/process/js/pr_organization.js
process/static/process/js/pr_sankey.js
process/templates/process/admin_change_job.html
process/templates/process/dj-process.html
process/templates/process/object_delete.html
process/templates/process/object_diagram.html
process/templates/process/object_edit.html
process/templates/process/objects_list.html
process/templates/process/task_edit.html
process/templatetags/__init__.py
process/templatetags/dj_process_templatetags.py
process/templatetags/process_diagram.py
process/views/__init__.py
process/views/diagram.py
process/views/generic_views.py
process/views/job.py
process/views/jobtask.py
process/views/process.py
process/views/task.py
django_process-4.7.8.dist-info/METADATA
django_process-4.7.8.dist-info/WHEEL
django_process-4.7.8.dist-info/top_level.txt
django_process-4.7.8.dist-info/RECORD
